seisnn/__init__.py
seisnn/components.py
seisnn/core.py
seisnn/example_proto.py
seisnn/io.py
seisnn/logger.py
seisnn/plot.py
seisnn/qc.py
seisnn/sql.py
seisnn/ui.py
seisnn/utils.py
SeisNN-0.5.0.dev0.dist-info/LICENSE
SeisNN-0.5.0.dev0.dist-info/METADATA
SeisNN-0.5.0.dev0.dist-info/WHEEL
SeisNN-0.5.0.dev0.dist-info/top_level.txt
SeisNN-0.5.0.dev0.dist-info/RECORD
