Metadata-Version: 2.1
Name: SeisNN
Version: 0.5.0.dev0
Summary: Deep learning seismic phase picking project
Home-page: https://github.com/SeisNN/SeisNN
Author: jimmy
Author-email: jimmy60504@gmail.com
License: MIT
Platform: UNKNOWN
Classifier: Programming Language :: Python :: 3 :: Only
Classifier: Programming Language :: Python :: 3.6
Classifier: Operating System :: POSIX :: Linux
Classifier: License :: OSI Approved :: MIT License
Classifier: Topic :: Scientific/Engineering :: Artificial Intelligence
Classifier: Development Status :: 2 - Pre-Alpha
Requires-Python: >=3.6
License-File: LICENSE
